[
  {
    "id": "start",
    "text": "Диагностика Revit. Что проверить?",
    "keywords": ["start", "диагностика", "revit"],
    "buttons": [
      { "text": "1. Акселератор", "nextNodeId": "accelerator" },
      { "text": "2. Диск C", "nextNodeId": "disk" },
      { "text": "3. Браузер", "nextNodeId": "browser" },
      { "text": "4. Рабочие наборы", "nextNodeId": "worksets" },
      { "text": "5. Группы/чережи/виды", "nextNodeId": "unused" },
      { "text": "6. Вес хранилища", "nextNodeId": "storage" },
      { "text": "7. Аналитика модели", "nextNodeId": "analytics" },
      { "text": "8. Семейства", "nextNodeId": "families" },
      { "text": "Чек-лист (8 шагов)", "nextNodeId": "diag-step1" }
    ]
  },
  {
    "id": "accelerator",
    "text": "Включите Акселератор: ускоряет открытие файла из другого офиса на 40–60%.",
    "keywords": ["акселератор", "accelerator"],
    "buttons": [ { "text": "Вернуться", "nextNodeId": "start" } ]
  },
  {
    "id": "disk",
    "text": "Проверьте свободное место на диске C (системный). При нехватке тормозит всё.",
    "keywords": ["диск", "ssd", "место", "c"],
    "buttons": [ { "text": "Вернуться", "nextNodeId": "start" } ]
  },
  {
    "id": "browser",
    "text": "Закройте лишние вкладки браузера — они отъедают ОЗУ, которой питается Revit.",
    "keywords": ["браузер", "вкладки", "ozu", "ram"],
    "buttons": [ { "text": "Вернуться", "nextNodeId": "start" } ]
  },
  {
    "id": "worksets",
    "text": "Рабочие наборы: элементы должны принадлежать своим РН, особенно арматура КЖ и связи. Минимум — РН связанных файлов других разделов. Это ускоряет открытие.",
    "keywords": ["workset", "worksets", "рн", "рабочие наборы"],
    "buttons": [ { "text": "Вернуться", "nextNodeId": "start" } ]
  },
  {
    "id": "unused",
    "text": "Проверьте неиспользуемые группы, чертежи САПР (dwg), виды. Они сидят в весе файла и обновляются фоном. Решение — удалить/оптимизировать после согласования с проектировщиком/БИМ-координатором.",
    "keywords": ["группы", "dwg", "виды", "чертежи"],
    "buttons": [ { "text": "Вернуться", "nextNodeId": "start" } ]
  },
  {
    "id": "storage",
    "text": "Вес файла хранилища (ФХ) для командной работы — около 300–500 МБ. БИМ-координатор может пересохранить со сжатием до 200–300 МБ.",
    "keywords": ["фх", "хранилище", "storage", "вес"],
    "buttons": [ { "text": "Вернуться", "nextNodeId": "start" } ]
  },
  {
    "id": "analytics",
    "text": "Аналитические данные модели (соединения, расчёты систем, объём помещений, аналитическая модель КЖ) обновляются фоном. Их можно отключить вместе с БИМ-координатором, если не нужны.",
    "keywords": ["аналитика", "соединения", "расчет", "системы", "объем помещений"],
    "buttons": [ { "text": "Вернуться", "nextNodeId": "start" } ]
  },
  {
    "id": "families",
    "text": "Используйте корпоративную библиотеку семейств. Сторонние/производителей передавайте БИМ-координатору для оптимизации веса и влияния на модель.",
    "keywords": ["семейства", "families", "библиотека"],
    "buttons": [ { "text": "Вернуться", "nextNodeId": "start" } ]
  },
  {
    "id": "diag-step1",
    "text": "Шаг 1/8: Включите Акселератор (ускоряет открытие из другого офиса на 40–60%).",
    "keywords": ["акселератор", "accelerator", "чеклист"],
    "buttons": [
      { "text": "Далее (2/8)", "nextNodeId": "diag-step2" },
      { "text": "К началу", "nextNodeId": "start" }
    ]
  },
  {
    "id": "diag-step2",
    "text": "Шаг 2/8: Проверьте свободное место на диске C (системный). При нехватке тормозит всё.",
    "keywords": ["диск", "ssd", "место", "c", "чеклист"],
    "buttons": [
      { "text": "Далее (3/8)", "nextNodeId": "diag-step3" },
      { "text": "К началу", "nextNodeId": "start" }
    ]
  },
  {
    "id": "diag-step3",
    "text": "Шаг 3/8: Закройте лишние вкладки браузера — они отъедают ОЗУ, которой питается Revit.",
    "keywords": ["браузер", "вкладки", "ozu", "ram", "чеклист"],
    "buttons": [
      { "text": "Далее (4/8)", "nextNodeId": "diag-step4" },
      { "text": "К началу", "nextNodeId": "start" }
    ]
  },
  {
    "id": "diag-step4",
    "text": "Шаг 4/8: Рабочие наборы: элементы должны принадлежать своим РН, особенно арматура КЖ и связи. Минимум — РН связанных файлов других разделов.",
    "keywords": ["workset", "worksets", "рн", "рабочие наборы", "чеклист"],
    "buttons": [
      { "text": "Далее (5/8)", "nextNodeId": "diag-step5" },
      { "text": "К началу", "nextNodeId": "start" }
    ]
  },
  {
    "id": "diag-step5",
    "text": "Шаг 5/8: Удалите/оптимизируйте неиспользуемые группы, чертежи САПР (dwg) и виды — они увеличивают вес файла и обновляются фоном.",
    "keywords": ["группы", "dwg", "виды", "чертежи", "чеклист"],
    "buttons": [
      { "text": "Далее (6/8)", "nextNodeId": "diag-step6" },
      { "text": "К началу", "nextNodeId": "start" }
    ]
  },
  {
    "id": "diag-step6",
    "text": "Шаг 6/8: Проверьте вес хранилища (ФХ): для командной работы обычно 300–500 МБ. БИМ-координатор может пересохранить со сжатием (до ~200–300 МБ).",
    "keywords": ["фх", "хранилище", "storage", "вес", "чеклист"],
    "buttons": [
      { "text": "Далее (7/8)", "nextNodeId": "diag-step7" },
      { "text": "К началу", "nextNodeId": "start" }
    ]
  },
  {
    "id": "diag-step7",
    "text": "Шаг 7/8: Аналитические данные модели (соединения, расчёты систем, объём помещений, аналитическая модель КЖ) обновляются фоном. Отключайте, если не нужны, вместе с БИМ-координатором.",
    "keywords": ["аналитика", "соединения", "расчет", "системы", "объем помещений", "чеклист"],
    "buttons": [
      { "text": "Далее (8/8)", "nextNodeId": "diag-step8" },
      { "text": "К началу", "nextNodeId": "start" }
    ]
  },
  {
    "id": "diag-step8",
    "text": "Шаг 8/8: Семейства — используйте корпоративную библиотеку. Сторонние передавайте БИМ-координатору для оптимизации веса и влияния на модель.",
    "keywords": ["семейства", "families", "библиотека", "чеклист"],
    "buttons": [
      { "text": "Завершить", "nextNodeId": "start" }
    ]
  }
]
